README.rst
setup.py
django_cloud_essentials/__init__.py
django_cloud_essentials/config.py
django_cloud_essentials/models.py
django_cloud_essentials.egg-info/PKG-INFO
django_cloud_essentials.egg-info/SOURCES.txt
django_cloud_essentials.egg-info/dependency_links.txt
django_cloud_essentials.egg-info/not-zip-safe
django_cloud_essentials.egg-info/requires.txt
django_cloud_essentials.egg-info/top_level.txt
django_cloud_essentials/monkeypatches/__init__.py
django_cloud_essentials/monkeypatches/hide_secrets_in_debug_mode.py