Metadata-Version: 1.0
Name: django-cloud-essentials
Version: 0.0.2
Summary: An opinionated django setup for Divio Cloud
Home-page: https://www.divio.com
Author: Divio AG
Author-email: info@divio.ch
License: UNKNOWN
Platform: UNKNOWN
